ESRF_ID10_SURF/__init__.py
ESRF_ID10_SURF/cli.py
ESRF_ID10_SURF/gui.py
ESRF_ID10_SURF/GID/GID.py
ESRF_ID10_SURF/GID/__init__.py
ESRF_ID10_SURF/GIXS/GIXS.py
ESRF_ID10_SURF/GIXS/__init__.py
ESRF_ID10_SURF/XRR/XRR.py
ESRF_ID10_SURF/XRR/__init__.py
esrf_id10_surf-0.1.6.dist-info/licenses/LICENSE
esrf_id10_surf-0.1.6.dist-info/METADATA
esrf_id10_surf-0.1.6.dist-info/WHEEL
esrf_id10_surf-0.1.6.dist-info/entry_points.txt
esrf_id10_surf-0.1.6.dist-info/top_level.txt
esrf_id10_surf-0.1.6.dist-info/RECORD
