Metadata-Version: 2.4
Name: esrf_id10_surf
Version: 0.1.6
Summary: A package for analyzing surface X-ray scattering data from the ID10-SURF beamline at the ESRF.
Author-email: "Egor A. Bersenev" <egor.bersenev@esrf.fr>
Project-URL: Homepage, https://chelberserker.github.io/ESRF_ID10_SURF/
Project-URL: Documentation, https://chelberserker.github.io/ESRF_ID10_SURF/
Project-URL: Repository, https://github.com/chelberserker/ESRF_ID10_SURF
Keywords: X-ray reflectivity,reflectometry,ESRF-ID10-SURF,ESRF ID10,ESRF,ID10,X-ray,reflectivity,GID,XRR,Grazing Incidence Diffraction,GISAXS,GIXS
Classifier: Programming Language :: Python :: 3
Classifier: License :: OSI Approved :: MIT License
Classifier: Operating System :: OS Independent
Requires-Python: >=3.8
License-File: LICENSE
Requires-Dist: numpy
Requires-Dist: matplotlib
Requires-Dist: h5py
Requires-Dist: lmfit
Requires-Dist: scipy
Requires-Dist: orsopy
Requires-Dist: PyYAML
Dynamic: license-file
